<?xml version="1.0" encoding="utf-8"?>
<odoo>
    <data noupdate="1">

        <!-- Scheduled Action to change task state to '1_done' daily -->
        <record id="ir_cron_set_tasks_to_done" model="ir.cron">
            <field name="name">Set Tasks to Done</field>
            <field name="model_id" ref="project.model_project_task"/>
            <field name="state">code</field>
            <field name="code">model._cron_set_tasks_to_done()</field>
            <field name="interval_number">1</field>
            <field name="interval_type">days</field>
            <field name="numbercall">-1</field>
            <field name="doall" eval="False"/>
            <field name="active" eval="True"/>
        </record>

    </data>
</odoo>
