<?xml version="1.0" encoding="utf-8"?>
<odoo>
    <template id="product_price_inherit">
        <t t-set="currency_usd_id" t-value="currency_usd_id"/>
        <div itemprop="offers" itemscope="itemscope" itemtype="http://schema.org/Offer"
             t-attf-class="product_price mt-2 mb-3 {{'d-none' if combination_info['prevent_zero_price_sale'] else 'd-inline-block'}}">
            <h3 class="css_editable_mode_hidden">
                <span class="oe_price"
                      style="white-space: nowrap;"
                      t-out="combination_info['price']"
                      t-options="{'widget': 'monetary', 'display_currency': currency_usd_id}"/>
                <span itemprop="price" style="display:none;" t-out="combination_info['price']"/>
                <span itemprop="priceCurrency" style="display:none;" t-esc="currency_usd_id.name"/>
                <span t-attf-class="text-danger oe_default_price ms-1 h5 {{'' if combination_info['has_discounted_price'] and not combination_info['compare_list_price'] else 'd-none'}}"
                      style="text-decoration: line-through; white-space: nowrap;"
                      t-esc="combination_info['list_price']"
                      t-options="{'widget': 'monetary', 'display_currency': currency_usd_id}"
                      itemprop="listPrice"
                />
                <t t-if="is_view_active('website_sale.tax_indication')" t-call="website_sale.tax_indication"/>
                <del t-if="combination_info['compare_list_price'] and (combination_info['compare_list_price'] &gt; combination_info['price'])">
                    <bdi dir="inherit">
                        <span t-esc="combination_info['compare_list_price']"
                              groups="website_sale.group_product_price_comparison"
                              t-options="{'widget': 'monetary', 'display_currency': currency_usd_id}"/>
                    </bdi>
                </del>
            </h3>
            <h3 class="css_non_editable_mode_hidden decimal_precision"
                t-att-data-precision="str(currency_usd_id.decimal_places)">
                <span t-field="product.list_price"
                      t-options="{'widget': 'monetary', 'display_currency': product.currency_id}"/>
                <t t-if="is_view_active('website_sale.tax_indication')" t-call="website_sale.tax_indication"/>
                <del t-if="combination_info['compare_list_price'] and (combination_info['compare_list_price'] &gt; combination_info['price'])">
                    <bdi dir="inherit">
                        <span t-field="product.compare_list_price"
                              groups="website_sale.group_product_price_comparison"
                              t-options="{'widget': 'monetary', 'display_currency': product.currency_id}"/>
                    </bdi>
                </del>
            </h3>
        </div>
        <div id="product_unavailable"
             t-attf-class="{{'d-flex' if combination_info['prevent_zero_price_sale'] else 'd-none'}}">
            <h3 class="fst-italic" t-field="website.prevent_zero_price_sale_text"/>
        </div>
    </template>
    <template id="custom_product_template" inherit_id="website_sale.product">
        <xpath expr="//section[@id='product_detail']" position="replace">
            <section id="product_detail"
                     t-attf-class="container py-4 oe_website_sale #{'discount' if combination_info['has_discounted_price'] else ''}"
                     t-att-data-view-track="view_track and '1' or '0'"
                     t-att-data-product-tracking-info="'product_tracking_info' in combination_info and json.dumps(combination_info['product_tracking_info'])"
            >
                <div class="row align-items-center">
                    <div class="col-lg-6 d-flex align-items-center">
                        <div class="d-flex justify-content-between w-100">
                            <t t-if="is_view_active('website_sale.search')" t-call="website_sale.search">
                                <t t-set="search" t-value="False"/>
                                <t t-set="_form_classes" t-valuef="mb-2 mb-lg-0"/>
                                <t t-set="_classes" t-value="'me-sm-2'"/>
                            </t>
                            <t t-set="website_sale_pricelists"
                               t-value="website.get_pricelist_available(show_visible=True)"/>
                            <t t-set="hasPricelistDropdown"
                               t-value="website_sale_pricelists and len(website_sale_pricelists)&gt;1"/>
                            <t t-call="website_sale.pricelist_list">
                                <t t-set="_classes" t-valuef="d-lg-inline ms-2"/>
                            </t>
                        </div>
                    </div>
                    <div class="col-lg-6 d-flex align-items-center">
                        <ol class="breadcrumb p-0 mb-2 m-lg-0">
                            <li class="breadcrumb-item o_not_editable">
                                <a t-att-href="keep(category=0)">All Services</a>
                            </li>
                            <li t-nocache="The category does not have to be cached, as the product can be accessed via different paths."
                                t-if="category" class="breadcrumb-item">
                                <a t-att-href="keep('/shop/category/%s' % slug(category), category=0)"
                                   t-field="category.name"/>
                            </li>
                            <li class="breadcrumb-item active">
                                <span t-field="product.name"/>
                            </li>
                        </ol>
                    </div>
                </div>
                <form t-if="product._is_add_to_cart_possible()" action="/shop/cart/update" method="POST">
                    <div class="row" id="product_detail_main" data-name="Product Page"
                         t-att-data-image_width="website.product_page_image_width"
                         t-att-data-image_layout="website.product_page_image_layout">
                        <t t-set="image_cols" t-value="website._get_product_page_proportions()"/>
                        <div t-attf-class="col-lg-#{image_cols[0]} mt-lg-4 o_wsale_product_images position-relative">
                            <table style="width: 100%; border-collapse: collapse; font-family: Arial, sans-serif;">
                                <tbody>
                                    <tr style="border-bottom: 1px solid #ddd;">
                                        <td style="padding: 10px; text-align: left;" colspan="2">
                                            <strong>From:</strong>
                                            <t t-esc="product.pol_id.display_name"/>
                                        </td>
                                        <td style="padding: 10px; text-align: left;" colspan="2">
                                            <strong>To:</strong>
                                            <t t-esc="product.pod_id.display_name"/>
                                        </td>
                                    </tr>
                                    <tr style="border-bottom: 1px solid #ddd;">
                                        <td style="padding: 10px; text-align: left;" colspan="2">
                                            <strong t-if="product.transport_type_id.id not in [1, 2, 3] or product.shipment_scope_id.id in [1, 3] or (product.transport_type_id.id in [2, 3] and not product.shipment_scope_id)">
                                                Container Type:
                                            </strong>
                                            <strong t-if="product.transport_type_id.id in [1] or product.shipment_scope_id.id not in [1,3]">
                                                Package Type:
                                            </strong>
                                            <t t-if="product.transport_type_id.id in [1] or product.shipment_scope_id.id not in [1,3]"
                                               t-esc="product.package_type.name"/>
                                            <t t-if="product.transport_type_id.id not in [1, 2, 3] or product.shipment_scope_id.id in [1, 3] or (product.transport_type_id.id in [2, 3] and not product.shipment_scope_id)"
                                               t-esc="product.container_type.name"/>
                                        </td>
                                        <td style="padding: 10px; text-align: left;" colspan="2">
                                            <strong t-if="product.transport_type_id.id in [2] and product.show_shipping_line">
                                                Shipping line:
                                            </strong>
                                            <strong t-if="product.transport_type_id.id in [1] and product.show_air_line">
                                                Air line:
                                            </strong>
                                            <t t-if="product.transport_type_id.id in [1]"
                                               t-esc="product.air_line.name"/>
                                            <t t-if="product.transport_type_id.id in [2]"
                                               t-esc="product.shipping_line.name"/>
                                        </td>
                                    </tr>
                                    <tr style="border-bottom: 1px solid #ddd;">
                                        <td style="padding: 10px; text-align: left;" colspan="2">
                                            <strong>Transit Time:</strong>
                                            <t t-esc="product.transit_time_duration"/>
                                        </td>
                                        <td style="padding: 10px; text-align: left;" colspan="2">
                                            <strong>Service:</strong>
                                            <t t-esc="', '.join([scope.name for scope in product.scope_ids])"/>
                                        </td>
                                    </tr>
                                    <tr style="border-bottom: 1px solid #ddd;">
                                        <td style="padding: 10px; text-align: left;" colspan="2">
                                            <strong t-if="product.transport_type_id.id in [2] and product.free_time_duration > 0 and product.shipment_scope_id.id in [1, 3]">
                                                Free Time:
                                            </strong>
                                            <t t-if="product.transport_type_id.id in [2] and product.free_time_duration > 0 and product.shipment_scope_id.id in [1, 3]"
                                               t-esc="product.free_time_duration"/>
                                        </td>
                                        <td style="padding: 10px; text-align: left;" colspan="2">
                                            <strong>Valid To:</strong>
                                            <t t-esc="product.expiration_date"/>
                                        </td>
                                    </tr>
                                    <tr>
                                        <td colspan="4">
                                            <br/>
                                        </td>
                                    </tr>
                                    <tr t-if="product.plane_line_ids or product.vessel_line_ids">
                                        <td colspan="4">
                                            <strong t-if="product.transport_type_id.id in [1]"
                                                    style="color: #6495ED;">Planes:
                                            </strong>

                                            <strong t-if="product.transport_type_id.id not in [1]"
                                                    style="color: #6495ED;">Vessels:
                                            </strong>
                                        </td>
                                    </tr>
                                    <tr t-if="product.plane_line_ids or product.vessel_line_ids">
                                        <td style="text-align: left;border-bottom: 1px solid #ddd;">
                                            <strong t-if="product.transport_type_id.id in [1]">Plane</strong>
                                            <strong t-if="product.transport_type_id.id not in [1]">Vessel Name</strong>
                                        </td>
                                        <td style="text-align: left;border-bottom: 1px solid #ddd;">
                                            <strong t-if="product.transport_type_id.id in [1]">Flight No.</strong>
                                            <strong t-if="product.transport_type_id.id not in [1]">Voyage No.</strong>
                                        </td>
                                        <td style="text-align: left;border-bottom: 1px solid #ddd;">
                                            <strong>ETD</strong>
                                        </td>
                                        <td style="text-align: left;border-bottom: 1px solid #ddd;">
                                            <strong>ETA</strong>
                                        </td>
                                        <td style="text-align: left;border-bottom: 1px solid #ddd;">
                                            <strong>T.T</strong>
                                        </td>
                                    </tr>
                                    <t t-foreach="product.plane_line_ids" t-as="plane">
                                        <tr>
                                            <td style="padding: 10px;border-bottom: 1px solid #ddd;">
                                                <t t-esc="plane.plane_id.name"/>
                                            </td>
                                            <td style="padding: 10px;border-bottom: 1px solid #ddd;">
                                                <t t-esc="plane.voyage_number"/>
                                            </td>
                                            <td style="padding: 10px;border-bottom: 1px solid #ddd;">
                                                <t t-esc="plane.etd"/>
                                            </td>
                                            <td style="padding: 10px;border-bottom: 1px solid #ddd;">
                                                <t t-esc="plane.eta"/>
                                            </td>
                                            <td style="padding: 10px;border-bottom: 1px solid #ddd;">
                                                <t t-esc="plane.tt_day"/>
                                            </td>
                                        </tr>
                                    </t>
                                    <t t-foreach="product.vessel_line_ids" t-as="vessel">
                                        <tr>
                                            <td style="padding: 10px;border-bottom: 1px solid #ddd;">
                                                <t t-esc="vessel.vessel_id.name"/>
                                            </td>
                                            <td style="padding: 10px;border-bottom: 1px solid #ddd;">
                                                <t t-esc="vessel.voyage_number"/>
                                            </td>
                                            <td style="padding: 10px;border-bottom: 1px solid #ddd;">
                                                <t t-esc="vessel.etd"/>
                                            </td>
                                            <td style="padding: 10px;border-bottom: 1px solid #ddd;">
                                                <t t-esc="vessel.eta"/>
                                            </td>
                                            <td style="padding: 10px;border-bottom: 1px solid #ddd;">
                                                <t t-esc="vessel.tt_day"/>
                                            </td>
                                        </tr>
                                    </t>
                                </tbody>
                            </table>

                        </div>
                        <div t-attf-class="col-lg-#{image_cols[1]} mt-md-4" id="product_details">
                            <t t-set="base_url" t-value="product.get_base_url()"/>
                            <table width="100%">
                                <tr>
                                    <td>
                                        <br/>
                                    </td>
                                </tr>
                                <tr>
                                    <td>

                                        <h3 class="css_editable_mode_hidden">
                                            <strong class="d-block">
                                                <span t-field="product.name"/>
                                            </strong>
                                        </h3>
                                    </td>
                                    <td align="right">

                                        <div class="transport-badge">
                                            <t t-out="product.transport_type_id.name"/>
                                        </div>

                                        <style>
                                            .transport-badge {
                                            background-color: #007bba; /* Blue color */
                                            color: white; /* White text color */
                                            padding: 10px 40px; /* Increased padding for width */
                                            border-radius: 4px; /* Rounded corners */
                                            display: inline-block; /* Make it an inline-block element */
                                            font-weight: bold; /* Make the text bold */
                                            text-align: center; /* Center the text */
                                            min-width: 120px; /* Minimum width to make it wider */
                                            }
                                        </style>

                                    </td>
                                </tr>
                                <tr>
                                    <td>
                                        <a href="#o_product_page_reviews"
                                           class="o_product_page_reviews_link text-decoration-none">
                                            <t t-call="portal_rating.rating_widget_stars_static">
                                                <t t-set="rating_avg" t-value="product.rating_avg"/>
                                                <t t-set="trans_text_plural">%s reviews</t>
                                                <t t-set="trans_text_singular">%s review</t>
                                                <t t-set="rating_count"
                                                   t-value="(trans_text_plural if product.rating_count > 1 else trans_text_singular) % product.rating_count"/>
                                            </t>
                                        </a>
                                    </td>
                                </tr>
                                <tr>
                                    <td>
                                        <br/>
                                    </td>
                                </tr>
                                <tr>
                                    <td>
                                        <t t-call="eit_freight_pricing.product_price_inherit"/>
                                    </td>
                                    <td align="right">
                                        <div id="o_wsale_cta_wrapper" class="d-flex flex-wrap align-items-center">
                                            <t t-set="hasQuantities" t-value="true"/>
                                            <t t-set="hasBuyNow" t-value="false"/>
                                            <t t-set="ctaSizeBig" t-value="not hasQuantities or not hasBuyNow"/>
                                            <div t-attf-class="css_quantity input-group {{'d-none' if combination_info['prevent_zero_price_sale'] else 'd-inline-flex'}} me-2 mb-2 align-middle"
                                                 contenteditable="false">
                                                <a t-attf-href="#" class="btn btn-link js_add_cart_json"
                                                   aria-label="Remove one" title="Remove one">
                                                    <i class="fa fa-minus"></i>
                                                </a>
                                                <input type="text" class="form-control quantity text-center"
                                                       data-min="1"
                                                       name="add_qty" t-att-value="add_qty or 1"/>
                                                <a t-attf-href="#" class="btn btn-link float_left js_add_cart_json"
                                                   aria-label="Add one" title="Add one">
                                                    <i class="fa fa-plus"></i>
                                                </a>
                                            </div>

                                            <div id="product_option_block" class="d-flex flex-wrap w-100"/>
                                        </div>
                                    </td>
                                </tr>
                            </table>
                            <br/>
                            <br/>
                            <table style="width: 100%; border-collapse: collapse; font-family: Arial, sans-serif;">
                                <thead style="background-color: #f4f4f4;">
                                    <tr style="border-bottom: 2px solid #ccc;">
                                        <th style="padding: 10px; text-align: left; font-weight: bold; color: #333;">
                                            Charge Type
                                        </th>
                                        <th style="padding: 10px; text-align: left; font-weight: bold; color: #333;">
                                            Rate
                                        </th>
                                        <th style="padding: 10px; text-align: left; font-weight: bold; color: #333;">
                                            Currency
                                        </th>
                                    </tr>
                                </thead>
                                <tbody>
                                    <t t-foreach="product.pricing_charge_ids" t-as="charge">
                                        <tr style="border-bottom: 1px solid #ddd;">
                                            <td style="padding: 10px; text-align: left;">
                                                <t t-esc="charge.product_id_2.name"/>
                                            </td>
                                            <td style="padding: 10px; text-align: left;">
                                                <t t-esc="charge.sale_price"/>
                                            </td>
                                            <td style="padding: 10px; text-align: left;">
                                                <t t-esc="charge.currency_id.name"/>
                                            </td>
                                        </tr>
                                    </t>
                                    <!-- Repeat tr as necessary -->
                                </tbody>
                            </table>
                            <br/>
                            <br/>
                            <br/>
                            <div style="width: 100%; text-align: left; padding-left: 30px">
                                <div id="add_to_cart_wrap"
                                     t-attf-class="{{'d-none' if combination_info['prevent_zero_price_sale'] else 'd-inline-flex'}} align-items-center mb-2 me-auto">
                                    <a data-animation-selector=".o_wsale_product_images" role="button"
                                       id="add_to_cart"
                                       t-attf-class="btn btn-primary js_check_product a-submit flex-grow-1"
                                       href="#">
                                        <i class="fa fa-shopping-cart me-2"/>
                                        Add to Favorites
                                    </a>

                                    <a role="button" t-attf-class="btn btn-outline-primary o_we_buy_now ms-1 " href="#">
                                        <i class="fa fa-bolt me-2"/>
                                        Book now
                                    </a>
                                </div>
                            </div>
                            <span itemprop="url" style="display:none;" t-esc="base_url + product.website_url"/>
                            <span itemprop="image" style="display:none;"
                                  t-esc="base_url + website.image_url(product, 'image_1920')"/>
                            <p t-field="product.description_sale" class="text-muted my-2"
                               placeholder="A short description that will also appear on documents."/>
                            <div t-field="product.description_ecommerce" class="oe_structure"
                                 placeholder="A detailed, formatted description to promote your product on this page. Use '/' to discover more features."/>
                            <input type="hidden" name="csrf_token" t-att-value="request.csrf_token()"
                                   t-nocache="The csrf token must always be up to date."/>
                            <div class="js_product js_main_product mb-3">
                                <div>
                                    <small t-if="combination_info['base_unit_price']"
                                           class="ms-1 text-muted o_base_unit_price_wrapper d-none"
                                           groups="website_sale.group_show_uom_price">
                                        <t t-call='website_sale.base_unit_price'/>
                                    </small>
                                </div>
                                <t t-placeholder="select">
                                    <input type="hidden" class="product_id" name="product_id"
                                           t-att-value="product_variant.id"/>
                                    <input type="hidden" class="product_template_id" name="product_template_id"
                                           t-att-value="product.id"/>
                                    <input t-if="product.public_categ_ids.ids" type="hidden" class="product_category_id"
                                           name="product_category_id" t-att-value="product.public_categ_ids.ids[0]"/>
                                    <t t-call="website_sale.variants">
                                        <t t-set="ul_class" t-valuef="flex-column"/>
                                        <t t-set="parent_combination" t-value="None"/>
                                    </t>
                                </t>
                                <p t-if="True" class="css_not_available_msg alert alert-warning">This combination does
                                    not exist.
                                </p>

                                <div id="contact_us_wrapper"
                                     t-attf-class="{{'d-flex' if combination_info['prevent_zero_price_sale'] else 'd-none'}} oe_structure oe_structure_solo #{_div_classes}">
                                    <section class="s_text_block" data-snippet="s_text_block" data-name="Text">
                                        <div class="container">
                                            <a t-att-href="website.contact_us_button_url"
                                               class="btn btn-primary btn_cta">Contact Us
                                            </a>
                                        </div>
                                    </section>
                                </div>
                                <t t-if="is_view_active('website_sale.product_tags')"
                                   t-call="website_sale.product_tags">
                                    <t t-set="all_product_tags" t-value="product_variant.all_product_tag_ids"/>
                                </t>
                            </div>
                            <div id="product_attributes_simple">
                                <t t-set="single_value_attributes"
                                   t-value="product.valid_product_template_attribute_line_ids._prepare_single_value_for_display()"/>
                                <table t-attf-class="table table-sm text-muted {{'' if single_value_attributes else 'd-none'}}">
                                    <t t-foreach="single_value_attributes" t-as="attribute">
                                        <tr>
                                            <td>
                                                <span t-field="attribute.name"/>:
                                                <t t-foreach="single_value_attributes[attribute]" t-as="ptal">
                                                    <span t-field="ptal.product_template_value_ids._only_active().name"/>
                                                    <t t-if="not ptal_last">,</t>
                                                </t>
                                            </td>
                                        </tr>
                                    </t>
                                </table>
                            </div>
                            <t t-set="product_documents"
                               t-value="product.sudo().product_document_ids.filtered(lambda doc: doc.shown_on_product_page)"/>
                            <div id="product_documents" class="my-2" t-if="product_documents">
                                <h5>Documents</h5>
                                <t t-foreach="product_documents" t-as="document_sudo">
                                    <t t-set="attachment_sudo" t-value="document_sudo.ir_attachment_id"/>
                                    <t t-set="target" t-value="attachment_sudo.type == 'url' and '_blank' or '_self'"/>
                                    <t t-set="icon"
                                       t-value="attachment_sudo.type == 'url' and 'fa-link' or 'fa-download'"/>
                                    <div>
                                        <a t-att-href="'/shop/' + slug(product) + '/document/' + str(document_sudo.id)"
                                           t-att-target="target">
                                            <i t-att-class="'fa ' + icon"/>
                                            <t t-out="attachment_sudo.name"/>
                                        </a>
                                    </div>
                                </t>
                            </div>
                            <br/>
                            <br/>
                            <div id="o_product_terms_and_share"
                                 class="d-flex justify-content-between flex-column flex-md-row align-items-md-end mb-3">
                            </div>
                            <br/>
                            <br/>
                            <br/>
                            <div class="o_shop_discussion_rating" data-anchor='true'>
                                <section id="o_product_page_reviews" class="container pt32 pb32" data-anchor='true'>
                                    <a class="o_product_page_reviews_title d-flex justify-content-between text-decoration-none collapsed"
                                       type="button" data-bs-toggle="collapse"
                                       data-bs-target="#o_product_page_reviews_content" aria-expanded="false"
                                       aria-controls="o_product_page_reviews_content">
                                        <h3 class="mb32">Customer Reviews</h3>
                                        <i class="fa align-self-start"/>
                                    </a>
                                    <div id="o_product_page_reviews_content" class="collapse">
                                        <t t-call="portal.message_thread">
                                            <t t-set="object" t-value="product"/>
                                            <t t-set="display_rating" t-value="True"/>
                                            <t t-set="message_per_page" t-value="5"/>
                                            <t t-set="two_columns" t-value="true"/>
                                        </t>
                                    </div>
                                </section>
                            </div>
                        </div>
                    </div>
                </form>
                <p t-elif="not product.active" class="alert alert-warning">This product is no longer
                    available.
                </p>
                <p t-else="" class="alert alert-warning">This product has no valid combination.</p>
            </section>
        </xpath>
    </template>
    <template id="product_custom_text" inherit_id="website_sale.product_custom_text"
              name="Replace Terms and Conditions">
        <!-- Use XPath to find the appropriate element and replace its content -->
        <xpath expr="//p[@class='text-muted mb-0']" position="replace">
            <!-- New content that will replace the original paragraph -->
            <p t-if="product.condition_test" class="text-muted mb-0">
                <strong>Terms and Conditions</strong>
                <br/>
                <t t-esc="product.condition_test"/>
            </p>
        </xpath>
    </template>
    <template id="product_share_buttons_inherit_empty" inherit_id="website_sale.product_share_buttons"
              name="Set Empty Share Buttons">
    </template>
    <template id="products_item" inherit_id="website_sale.products_item" name="Products item">
        <xpath expr="//form" position="replace">
            <t t-set="currency_usd_id" t-value="currency_usd_id"/>
            <form action="/shop/cart/update" method="post" class="oe_product_cart h-100 d-flex"
                  t-att-data-publish="product.website_published and 'on' or 'off'"
                  itemscope="itemscope" itemtype="http://schema.org/Product">

                <t t-set="product_href"
                   t-value="keep(product.website_url, page=(pager['page']['num'] if pager['page']['num']&gt;1 else None))"/>
                <t t-set="image_type"
                   t-value="product._get_suitable_image_size(ppr, td_product['x'], td_product['y'])"/>

                <div class="oe_product_image position-relative h-100 flex-grow-0 overflow-hidden">
                    <input type="hidden" name="csrf_token" t-att-value="request.csrf_token()"
                           t-nocache="The csrf token must always be up to date."/>
                    <a t-att-href="product_href" class="oe_product_image_link d-block h-100 position-relative"
                       itemprop="url" contenteditable="false">
                        <t t-set="image_holder" t-value="product._get_image_holder()"/>
                        <span t-field="image_holder.image_1920"
                              t-options="{'widget': 'image', 'preview_image': image_type, 'itemprop': 'image', 'class': 'h-100 w-100 position-absolute'}"
                              class="oe_product_image_img_wrapper d-flex h-100 justify-content-center align-items-center position-absolute"/>

                        <t t-set="bg_color" t-value="td_product['ribbon']['bg_color'] or ''"/>
                        <t t-set="text_color" t-value="td_product['ribbon']['text_color']"/>
                        <t t-set="bg_class" t-value="td_product['ribbon']['html_class']"/>
                        <span t-attf-class="o_ribbon o_not_editable #{bg_class}"
                              t-attf-style="#{text_color and ('color: %s; ' % text_color)}#{bg_color and 'background-color:' + bg_color}"
                              t-out="td_product['ribbon']['html'] or ''"/>
                    </a>
                </div>
                <div class="o_wsale_product_information position-relative d-flex flex-column flex-grow-1 flex-shrink-1">
                    <div class="o_wsale_product_information_text flex-grow-1">
                        <h6 class="o_wsale_products_item_title mb-2">
                            <a class="text-primary text-decoration-none" itemprop="name" t-att-href="product_href"
                               t-att-content="product.name" t-field="product.name"/>
                            <a t-if="not product.website_published" role="button" t-att-href="product_href"
                               class="btn btn-sm btn-danger" title="This product is unpublished.">
                                Unpublished
                            </a>
                        </h6>

                        <!-- Updated From/To Layout using Flexbox -->
                        <div class="d-flex justify-content-between">
                            <div>
                                <strong>From:</strong>
                                <t t-esc="product.pol_id.display_name"/>
                            </div>
                            <div>
                                <strong>To:</strong>
                                <t t-esc="product.pod_id.display_name"/>
                            </div>
                        </div>
                        <br/>
                        <div class="d-flex justify-content-between">
                            <div>
                                <strong t-if="product.transport_type_id.id not in [1, 2, 3] or product.shipment_scope_id.id in [1, 3] or (product.transport_type_id.id in [2, 3] and not product.shipment_scope_id)">
                                    Container Type:
                                </strong>
                                <strong t-if="product.transport_type_id.id in [1] or product.shipment_scope_id.id not in [1,3]">
                                    Package Type:
                                </strong>
                                <t t-if="product.transport_type_id.id in [1] or product.shipment_scope_id.id not in [1,3]"
                                   t-esc="product.package_type.name"/>
                                <t t-if="product.transport_type_id.id not in [1, 2, 3] or product.shipment_scope_id.id in [1, 3] or (product.transport_type_id.id in [2, 3] and not product.shipment_scope_id)"
                                   t-esc="product.container_type.name"/>

                            </div>
                            <div>
                                <strong>Transit Time:</strong>
                                <t t-esc="product.transit_time_duration"/>
                            </div>
                        </div>
                        <br/>
                        <div class="d-flex justify-content-between">
                            <div>
                                <strong>Service:</strong>
                                <t t-esc="', '.join([scope.name for scope in product.scope_ids])"/>
                            </div>
                            <div>
                                <strong>Valid To:</strong>
                                <t t-esc="product.expiration_date"/>
                            </div>
                        </div>

                    </div>
                    <br/>
                    <div class="o_wsale_product_sub d-flex justify-content-between align-items-end gap-2 flex-wrap pb-1">
                        <t t-set="template_price_vals" t-value="get_product_prices(product)"/>
                        <div class="o_wsale_product_btn"/>
                        <div class="product_price" itemprop="offers" itemscope="itemscope"
                             itemtype="http://schema.org/Offer">
                            <span class="h6 mb-0"
                                  t-if="template_price_vals['price_reduce'] or not website.prevent_zero_price_sale"
                                  t-esc="template_price_vals['price_reduce']"
                                  t-options="{'widget': 'monetary', 'display_currency': currency_usd_id}"/>
                            <span class="h6 mb-0" t-else="" t-field="website.prevent_zero_price_sale_text"/>
                            <span itemprop="price" style="display:none;" t-esc="template_price_vals['price_reduce']"/>
                            <span itemprop="priceCurrency" style="display:none;" t-esc="currency_usd_id.name"/>
                        </div>
                    </div>
                </div>
            </form>
        </xpath>
    </template>


    <template id="products_inherit" inherit_id="website_sale.products">
        <xpath expr="//div[@id='wrap']" position="replace">
            <div id="wrap" class="js_sale o_wsale_products_page">
                <div class="oe_structure oe_empty oe_structure_not_nearest" id="oe_structure_website_sale_products_1"/>
                <div class="container oe_website_sale pt-2">
                    <div class="row o_wsale_products_main_row align-items-start flex-nowrap">
                        <aside t-if="hasLeftColumn" id="products_grid_before"
                               class="d-none d-lg-block position-sticky col-3 px-3 clearfix">
                            <div class="o_wsale_products_grid_before_rail vh-100 ms-n2 mt-n2 pt-2 pe-lg-2 pb-lg-5 ps-2 overflow-y-scroll">
                                <div t-if="opt_wsale_categories" class="products_categories mb-3">
                                    <t t-call="website_sale.products_categories_list"/>
                                </div>
                                <div class="products_attributes_filters"/>
                                <t t-if="opt_wsale_filter_price and opt_wsale_attributes"
                                   t-call="website_sale.filter_products_price"/>
                            </div>
                        </aside>
                        <div id="products_grid"
                             t-attf-class="#{'o_wsale_layout_list' if layout_mode == 'list' else ''} {{'col-lg-9' if hasLeftColumn else 'col-12'}}">
                            <t t-call="website_sale.products_breadcrumb">
                                <t t-set="_classes" t-valuef="d-none d-lg-flex w-100 p-0 small"/>
                            </t>
                            <div class="products_header btn-toolbar flex-nowrap align-items-center justify-content-between gap-3 mb-3">
                                <t t-if="is_view_active('website_sale.search')" t-call="website_sale.search">
                                    <t t-set="search" t-value="original_search or search"/>
                                    <t t-set="_form_classes"
                                       t-valuef="d-lg-inline {{'d-inline' if not category else 'd-none'}}"/>
                                </t>

                                <t t-call="website_sale.pricelist_list" t-cache="pricelist">
                                    <t t-set="_classes" t-valuef="d-none d-lg-inline"/>
                                </t>

                                <t t-if="is_view_active('website_sale.sort')" t-call="website_sale.sort">
                                    <t t-set="_classes" t-valuef="d-none d-lg-inline-block"/>
                                </t>

                                <div t-if="category" class="d-flex align-items-center d-lg-none me-auto">
                                    <t t-if="not category.parent_id" t-set="backUrl" t-valuef="/shop"/>
                                    <t t-else="" t-set="backUrl"
                                       t-value="keep('/shop/category/' + slug(category.parent_id), category=0)"/>

                                    <a t-attf-class="btn btn-{{navClass}} me-2"
                                       t-att-href="category.parent_id and keep('/shop/category/' + slug(category.parent_id), category=0) or '/shop'">
                                        <i class="fa fa-angle-left"/>
                                    </a>
                                    <h4 t-out="category.name" class="mb-0 me-auto"/>
                                </div>

                                <t t-if="is_view_active('website_sale.add_grid_or_list_option')"
                                   t-call="website_sale.add_grid_or_list_option">
                                    <t t-set="_classes" t-valuef="d-flex"/>
                                </t>

                                <button t-if="is_view_active('website_sale.sort') or opt_wsale_categories or opt_wsale_attributes or opt_wsale_attributes_top"
                                        t-attf-class="btn btn-{{navClass}} position-relative {{not opt_wsale_attributes_top and 'd-lg-none'}}"
                                        data-bs-toggle="offcanvas"
                                        data-bs-target="#o_wsale_offcanvas">
                                    <i class="fa fa-sliders"/>
                                    <span t-if="isFilteringByPrice or attrib_set or tags"
                                          t-attf-class="position-absolute top-0 start-100 translate-middle border border-{{navClass}} rounded-circle bg-danger p-1">
                                        <span class="visually-hidden">filters active</span>
                                    </span>
                                </button>
                            </div>

                            <t t-if="opt_wsale_categories_top" t-call="website_sale.filmstrip_categories"/>

                            <div t-if="original_search and products" class="alert alert-warning mt8">
                                No results found for '<span t-esc="original_search"/>'. Showing results for '<span
                                    t-esc="search"/>'.
                            </div>

                            <t t-if="category">
                                <t t-set='editor_msg'>Drag building blocks here to customize the header for "<t
                                        t-esc='category.name'/>" category.
                                </t>
                                <div class="mb16" id="category_header" t-att-data-editor-message="editor_msg"
                                     t-field="category.website_description"/>
                            </t>

                            <div t-if="products" class="o_wsale_products_grid_table_wrapper pt-3 pt-lg-0">
                                <table class="table table-borderless h-100 m-0" t-att-data-ppg="ppg"
                                       t-att-data-ppr="ppr" t-att-data-default-sort="website.shop_default_sort"
                                       t-att-data-name="grid_block_name">
                                    <colgroup t-ignore="true">
                                        <!-- Force the number of columns (useful when only one row of (x < ppr) products) -->
                                        <col t-foreach="ppr" t-as="p"/>
                                    </colgroup>
                                    <tbody>
                                        <tr t-foreach="bins" t-as="tr_product">
                                            <t t-foreach="tr_product" t-as="td_product">
                                                <t t-if="td_product">
                                                    <!-- We use t-attf-class here to allow easier customization -->
                                                    <td t-att-colspan="td_product['x'] != 1 and td_product['x']"
                                                        t-att-rowspan="td_product['y'] != 1 and td_product['y']"
                                                        t-attf-class="oe_product"
                                                        t-att-data-ribbon-id="td_product['ribbon'].id"
                                                        t-att-data-name="product_block_name">
                                                        <div t-attf-class="o_wsale_product_grid_wrapper position-relative h-100 o_wsale_product_grid_wrapper_#{td_product['x']}_#{td_product['y']}">
                                                            <t t-call="website_sale.products_item">
                                                                <t t-set="product" t-value="td_product['product']"/>
                                                            </t>
                                                        </div>
                                                    </td>
                                                </t>
                                                <td t-else=""/>
                                            </t>
                                        </tr>
                                    </tbody>
                                </table>
                            </div>
                            <div t-nocache="get the actual search" t-else="" class="text-center text-muted mt128 mb256">
                                <t t-if="not search">
                                    <h3 class="mt8">No product defined</h3>
                                    <p t-if="category">No product defined in this category.</p>
                                </t>
                                <t t-else="">
                                    <h3 class="mt8">No results</h3>
                                    <p>No results for "<strong t-esc='search'/>"
                                        <t t-if="category">in category "<strong t-esc="category.display_name"/>"
                                        </t>
                                        .
                                    </p>
                                </t>
                                <p t-ignore="true" groups="sales_team.group_sale_manager">Click <i>'New'</i> in the
                                    top-right corner to create your first product.
                                </p>
                            </div>
                            <div class="products_pager d-flex justify-content-center pt-5 pb-3">
                                <t t-call="website.pager"/>
                            </div>
                        </div>
                    </div>

                    <t t-call="website_sale.o_wsale_offcanvas"/>
                </div>
                <div class="oe_structure oe_empty oe_structure_not_nearest" id="oe_structure_website_sale_products_2"/>
            </div>
        </xpath>
    </template>


    <template id="cart_lines_inherit" inherit_id="website_sale.cart_lines" name="Shopping Cart Lines">
        <xpath expr="//div[@id='cart_products']" position="replace">
            <t t-set="currency_usd_id" t-value="currency_usd_id"/>
            <div id="cart_products"
                 t-if="website_sale_order and website_sale_order.website_order_line"
                 class="js_cart_lines d-flex flex-column mb32">
                <t t-set="show_qty" t-value="is_view_active('website_sale.product_quantity')"/>
                <t t-set="currency_usd_id" t-value="currency_usd_id"/>
                <div t-foreach="website_sale_order.website_order_line"
                     t-as="line"
                     t-attf-class="o_cart_product d-flex align-items-stretch gap-3 #{line.linked_line_id and 'optional_product info'} #{not line_last and 'border-bottom pb-4'} #{line_index &gt; 0 and 'pt-4'}"
                     t-attf-data-product-id="#{line.product_id and line.product_id.id}">
                    <t t-if="line.product_id">
                        <img t-if="line._is_not_sellable_line() and line.product_id.image_128"
                             t-att-src="image_data_uri(line.product_id.image_128)"
                             class="o_image_64_max  img rounded"
                             t-att-alt="line.name_short"/>
                        <div t-else=""
                             t-field="line.product_id.image_128"
                             t-options="{'widget': 'image', 'qweb_img_responsive': False, 'class': 'o_image_64_max rounded'}"/>
                        <div class="flex-grow-1">
                            <t t-call="website_sale.cart_line_product_link">
                                <h6 t-field="line.name_short" class="d-inline align-top h6 fw-bold"/>
                            </t>
                            <t t-call="website_sale.cart_line_description_following_lines">
                                <t t-set="div_class" t-valuef="d-none d-md-block"/>
                            </t>
                            <div>
                                <a href='#'
                                   class="js_delete_product d-none d-md-inline-block small"
                                   aria-label="Remove from cart"
                                   title="Remove from cart">Remove
                                </a>
                                <button class="js_delete_product btn btn-light d-inline-block d-md-none"
                                        title="remove">
                                    <i class="fa fa-trash-o"/>
                                </button>
                            </div>
                        </div>
                        <div class="d-flex flex-column align-items-end">
                            <div t-attf-class="css_quantity input-group mb-2"
                                 name="website_sale_cart_line_quantity">
                                <t t-if="not line._is_not_sellable_line()">
                                    <t t-if="show_qty">
                                        <a href="#"
                                           class="js_add_cart_json btn btn-link d-inline-block border-end-0"
                                           aria-label="Remove one"
                                           title="Remove one">
                                            <i class="position-relative z-index-1 fa fa-minus"/>
                                        </a>
                                        <input type="text"
                                               class="js_quantity quantity form-control border-start-0 border-end-0"
                                               t-att-data-line-id="line.id"
                                               t-att-data-product-id="line.product_id.id"
                                               t-att-value="int(line.product_uom_qty) == line.product_uom_qty and int(line.product_uom_qty) or line.product_uom_qty"/>
                                        <t t-if="line._get_shop_warning(clear=False)">
                                            <a href="#" class="btn btn-link">
                                                <i class='fa fa-warning text-warning'
                                                   t-att-title="line._get_shop_warning()"
                                                   role="img"
                                                   aria-label="Warning"/>
                                            </a>
                                        </t>
                                        <a t-else=""
                                           href="#"
                                           class="js_add_cart_json d-inline-block float_left btn btn-link border-start-0"
                                           aria-label="Add one"
                                           title="Add one">
                                            <i class="fa fa-plus position-relative z-index-1"/>
                                        </a>
                                    </t>
                                    <t t-else="">
                                        <input type="hidden"
                                               class="js_quantity form-control quantity"
                                               t-att-data-line-id="line.id"
                                               t-att-data-product-id="line.product_id.id"
                                               t-att-value="int(line.product_uom_qty) == line.product_uom_qty and int(line.product_uom_qty) or line.product_uom_qty"/>
                                    </t>
                                </t>
                                <t t-else="">
                                    <span class="w-100 text-muted" t-esc="int(line.product_uom_qty)"/>
                                    <input type="hidden"
                                           class="js_quantity quantity form-control"
                                           t-att-data-line-id="line.id"
                                           t-att-data-product-id="line.product_id.id"
                                           t-att-value="line.product_uom_qty"/>
                                </t>
                            </div>
                            <div class="mb-0 h6 fw-bold text-end" name="website_sale_cart_line_price">
                                <t t-if="line.discount">
                                    <del t-attf-class="#{'text-danger mr8'}"
                                         style="white-space: nowrap;"
                                         t-out="line._get_displayed_unit_price() * line.product_uom_qty"
                                         t-options="{'widget': 'monetary', 'display_currency': currency_usd_id}"/>
                                </t>
                                <t t-if="website.show_line_subtotals_tax_selection == 'tax_excluded'"
                                   t-set='product_price'
                                   t-value='line.price_subtotal'/>
                                <t t-else=""
                                   t-set='product_price'
                                   t-value='line.price_total'/>
                                <span t-out="line.product_id.list_price" style="white-space: nowrap;"
                                      t-options="{'widget': 'monetary', 'display_currency': currency_usd_id}"/>
                                <!--                                <small t-if="not line._is_not_sellable_line() and line.product_id.base_unit_price"-->
                                <!--                                       class="cart_product_base_unit_price d-block text-muted"-->
                                <!--                                       groups="website_sale.group_show_uom_price">-->
                                <!--                                    <t t-call='website_sale.base_unit_price'>-->
                                <!--                                        <t t-set='product' t-value='line.product_id'/>-->
                                <!--                                        <t t-set='combination_info'-->
                                <!--                                           t-value="{'base_unit_price': product._get_base_unit_price(product_price/line.product_uom_qty)}"/>-->
                                <!--                                    </t>-->
                                <!--                                </small>-->
                            </div>
                        </div>
                    </t>
                </div>
            </div>
        </xpath>
    </template>

    <template id="total_inherit" inherit_id="website_sale.total">
        <xpath expr="//div[@id='cart_total']" position="replace">
            <div id="cart_total" t-if="website_sale_order and website_sale_order.website_order_line"
                 t-att-class="_cart_total_classes">
                <table class="table mb-0">
                    <tr id="order_total_untaxed">
                        <td id="cart_total_subtotal"
                            class="border-0 pb-2 ps-0 pt-0 text-start text-muted"
                            colspan="2">
                            Subtotal
                        </td>
                        <td class="text-end border-0 pb-2 pe-0 pt-0">
                            <span t-field="website_sale_order.amount_untaxed"
                                  class="monetary_field"
                                  style="white-space: nowrap;"
                                  t-options="{'widget': 'monetary', 'display_currency': website_sale_order.currency_id}"/>
                        </td>
                    </tr>
                    <tr id="order_total_taxes">
                        <td colspan="2" class="text-muted border-0 ps-0 pt-0 pb-3">Taxes</td>
                        <td class="text-end border-0 pe-0 pt-0 pb-3">
                            <span t-field="website_sale_order.amount_tax"
                                  class="monetary_field"
                                  style="white-space: nowrap;"
                                  t-options="{'widget': 'monetary', 'display_currency': website_sale_order.currency_id}"/>
                        </td>
                    </tr>
                    <tr id="order_total" class="border-top">
                        <td colspan="2" class="border-0 ps-0 pt-3">
                            <strong>Total</strong>
                        </td>
                        <td class="text-end border-0 px-0 pt-3">
                            <strong t-field="website_sale_order.amount_total"
                                    class="monetary_field text-end p-0"
                                    t-options="{'widget': 'monetary', 'display_currency': website_sale_order.currency_id}"/>
                        </td>
                    </tr>
                </table>
            </div>
        </xpath>
    </template>


    <!-- /shop/extra_info route -->
    <template id="extra_info_inherit" inherit_id="website_sale.extra_info">
        <xpath expr="//h3[contains(text(), 'Extra info')]" position="replace">
            <h3 class="mb-4">Booking Info</h3>
        </xpath>
        <xpath expr="//section[@class='s_website_form']" position="replace">
            <section class="s_website_form" data-vcss="001" data-snippet="s_website_form">
                <div class="container">
                    <form action="/website/form/" method="post" enctype="multipart/form-data"
                          class="o_mark_required s_website_form_no_recaptcha"
                          data-mark="*" data-force_action="shop.sale.order" data-model_name="sale.order"
                          data-success-mode="redirect" data-success-page="/shop/payment" hide-change-model="true">
                        <div class="s_website_form_rows s_col_no_bgcolor row">
                            <div class="s_website_form_field col-12 py-2 mb-0" data-type="char" data-name="Field">
                                <div class="s_col_no_resize s_col_no_bgcolor row">
                                    <label class="s_website_form_label col-form-label col-sm-auto" style="width: 200px"
                                           for="sale1">
                                        <span class="s_website_form_label_content">Your Reference</span>
                                    </label>
                                    <div class="col-sm">
                                        <input id="sale1" type="text" class="s_website_form_input form-control"
                                               name="client_order_ref"/>
                                    </div>
                                </div>
                            </div>
                            <div class="s_website_form_field s_website_form_custom col-12 py-2 mb-0" data-type="text"
                                 data-name="Field">
                                <div class="s_col_no_resize s_col_no_bgcolor row">
                                    <label class="s_website_form_label col-form-label col-sm-auto" style="width: 200px"
                                           for="sale2">
                                        <span class="s_website_form_label_content">Give us your feedback</span>
                                    </label>
                                    <div class="col-sm">
                                        <textarea id="sale2" class="s_website_form_input form-control"
                                                  name="Give us your feedback"/>
                                    </div>
                                </div>
                            </div>
                            <div class="s_website_form_field s_website_form_custom col-12 py-2 mb-0" data-type="binary"
                                 data-name="Field">
                                <div class="s_col_no_resize s_col_no_bgcolor row">
                                    <label class="s_website_form_label col-form-label col-sm-auto" style="width: 200px"
                                           for="sale3">
                                        <span class="s_website_form_label_content">Upload a document</span>
                                    </label>
                                    <div class="col-sm">
                                        <input id="sale3" type="file" class="s_website_form_input form-control"
                                               name="a_document"/>
                                    </div>
                                </div>
                            </div>
                            <div class="s_website_form_submit s_website_form_no_submit_option d-flex flex-column flex-lg-row align-items-lg-center pt-4">
                                <a role="button"
                                   name="website_sale_main_button"
                                   class="s_website_form_send btn btn-primary order-lg-3 w-100 w-lg-auto ms-lg-auto"
                                   href="/shop/confirm_order">
                                    Continue checkout
                                    <i class="fa fa-angle-right ms-2 fw-light"/>
                                </a>

                                <div class="position-relative d-flex d-lg-none w-100 justify-content-center align-items-center my-2 opacity-75">
                                    <hr class="w-100"/>
                                    <span class="px-3">or</span>
                                    <hr class="w-100"/>
                                </div>

                                <a href="/shop/checkout" class="text-center">
                                    <i class="fa fa-angle-left me-2 fw-light"/>
                                    Return to shipping
                                </a>
                                <span id="s_website_form_result"/>
                            </div>
                        </div>
                    </form>
                </div>
            </section>
        </xpath>
    </template>


    <!-- /shop/payment route -->
    <template id="payment_inherit" inherit_id="website_sale.payment">
        <xpath expr="//t[@name='website_sale_non_free_cart']" position="replace">

        </xpath>
    </template>

    <template id="confirmation_inherit" inherit_id="website_sale.confirmation">
        <xpath expr="//t[@t-call='website_sale.checkout_layout']" position="replace">
            <t t-call="website_sale.checkout_layout">
                <t t-set="show_wizard_checkout" t-value="False"/>
                <t t-set="show_navigation_button" t-value="False"/>
                <t t-set="show_footer" t-value="True"/>
                <t t-set="additional_title">Shop - Confirmed</t>
                <t t-set="hide_promotions" t-value="True"/>
                <t t-set="oe_structure">
                    <!-- This is the drag-and-drop area for website building blocs at the end of each
                         checkout page. This is append at the of the page in `checkout_layout`. The
                         templates created in the database to store blocs are hooked using XPath on the
                         `oe_struture` element ID. Therefore, we can't use dynamic IDs (like with
                         t-att-id) and each template needs to define a div element. -->
                    <div class="oe_structure" id="oe_structure_website_sale_confirmation_3"/>
                </t>

                <t t-set="tx_sudo" t-value="order.get_portal_last_transaction()"/>
                <div t-if="tx_sudo.state in ['pending', 'done']"
                     class="d-flex justify-content-between align-items-center">
                    <h3>Thank you for your order.</h3>
                    <a role="button" class="d-none d-md-inline-block btn btn-primary ms-auto" href="/shop/print"
                       target="_blank" aria-label="Print" title="Print"><i class="fa fa-print me-2"></i>Print
                    </a>
                </div>
                <t t-if="tx_sudo.state == 'done'">
                    <div class="mb-4">
                        <h5>
                            <em>
                                <span>Order</span>
                                <span t-field="order.name"/>
                                <t t-if="order.state == 'sale'">
                                    <i class="fa fa-check-circle ms-1"/>
                                </t>
                            </em>
                        </h5>
                    </div>
                </t>
                <t t-if="request.env['res.users']._get_signup_invitation_scope() == 'b2c' and request.website.is_public_user()">
                    <p class="alert alert-info mt-3" role="status">
                        <a role="button"
                           t-att-href="order.partner_id.signup_prepare() and order.partner_id.with_context(relative_url=True).signup_url"
                           class="btn btn-primary">Sign Up
                        </a>
                        to follow your order.
                    </p>
                </t>
                <div class="oe_structure clearfix mt-3" id="oe_structure_website_sale_confirmation_1"/>


                <div class="card mt-3">
                    <div class="card-body">
                        <t t-set="same_shipping"
                           t-value="bool(order.partner_shipping_id == order.partner_invoice_id or only_services)"/>
                        <div>
                            <b>Billing <t t-if="same_shipping and not only_services">&amp; Shipping</t>:
                            </b>
                            <span t-esc='order.partner_invoice_id'
                                  t-options="dict(widget='contact', fields=['address'], no_marker=True, separator=', ')"
                                  class="address-inline"/>
                        </div>
                        <div t-if="not same_shipping and not only_services"
                             groups="account.group_delivery_invoice_address">
                            <b>Shipping:</b>
                            <span t-esc='order.partner_shipping_id'
                                  t-options="dict(widget='contact', fields=['address'], no_marker=True, separator=', ')"
                                  class="address-inline"/>
                        </div>
                    </div>
                </div>
                <div class="oe_structure mt-3" id="oe_structure_website_sale_confirmation_2"/>
                <input t-if='website.plausible_shared_key' type='hidden' class='js_plausible_push'
                       data-event-name='Shop'
                       t-attf-data-event-params='{"CTA": "Order Confirmed", "amount": "#{"%3s-%3s" % (max(0, round(website_sale_order.amount_total/100)*100 - 50), round(website_sale_order.amount_total/100)*100 + 50)}"}'/>
            </t>
        </xpath>
    </template>

    <template id="payment_transaction_status" inherit_id="payment.transaction_status">
        <xpath expr="//div[@name='o_payment_status_alert']" position="replace">
        </xpath>
    </template>

</odoo>
